src/mcp_google_sheets/__init__.py
src/mcp_google_sheets/server.py
orange_mcp_google_sheets-0.2.0.dist-info/METADATA
orange_mcp_google_sheets-0.2.0.dist-info/WHEEL
orange_mcp_google_sheets-0.2.0.dist-info/entry_points.txt
orange_mcp_google_sheets-0.2.0.dist-info/licenses/LICENSE
orange_mcp_google_sheets-0.2.0.dist-info/RECORD
